pybuilder_noseallure/__init__.py
pybuilder_noseallure/tasks.py
pybuilder_noseallure/utils.py
pybuilder_noseallure-0.0.6.dist-info/DESCRIPTION.rst
pybuilder_noseallure-0.0.6.dist-info/METADATA
pybuilder_noseallure-0.0.6.dist-info/RECORD
pybuilder_noseallure-0.0.6.dist-info/WHEEL
pybuilder_noseallure-0.0.6.dist-info/metadata.json
pybuilder_noseallure-0.0.6.dist-info/namespace_packages.txt
pybuilder_noseallure-0.0.6.dist-info/top_level.txt
pybuilder_noseallure-0.0.6.dist-info/zip-safe
