Metadata-Version: 2.0
Name: pybuilder-noseallure
Version: 0.0.6
Summary: PyBuilder Nose Allure Plugin
Home-page: https://github.com/anukuls/pybuilder_noseallure
Author: Anukul Singhal
Author-email: anukul.singhal@gmail.com
License: Apache License, Version 2.0
Platform: UNKNOWN
Classifier: Development Status :: 3 - Alpha
Classifier: Programming Language :: Python
Requires-Dist: nose
Requires-Dist: nose-allure-plugin
